django_drf_jwt/__init__.py
django_drf_jwt/apps.py
django_drf_jwt/settings.py
django_drf_jwt/urls.py
django_drf_jwt-0.0.6.dist-info/LICENSE.md
django_drf_jwt-0.0.6.dist-info/METADATA
django_drf_jwt-0.0.6.dist-info/WHEEL
django_drf_jwt-0.0.6.dist-info/top_level.txt
django_drf_jwt-0.0.6.dist-info/RECORD
