Metadata-Version: 2.1
Name: django-drf-jwt
Version: 0.0.6
Summary: A simple app to demonstrate django-jwt-authentication using Django REST Framework
Home-page: https://github.com/ShahzaibMumtaz07/django_drf_jwt.git
Author: Shahzaib Mumtaz
Author-email: shahzaib.mumtaz.20195@gmail.com
License: MIT
Platform: UNKNOWN
Classifier: License :: OSI Approved :: MIT License
Classifier: Programming Language :: Python :: 3
License-File: LICENSE.md
Requires-Dist: Django (>=2.0.0)
Requires-Dist: djangorestframework (>=3.12.4)
Requires-Dist: djangorestframework-jwt (>=1.11.0)
